[
  {
    "id": 1,
    "first_name": "Jerrilee",
    "last_name": "McCarlie",
    "email": "jmccarlie0@dropbox.com",
    "gender": "Female",
    "carmodel": "Econoline E150"
  },
  {
    "id": 2,
    "first_name": "Ida",
    "last_name": "Matteacci",
    "email": "imatteacci1@mapquest.com",
    "gender": "Female",
    "carmodel": "Lumina"
  },
  {
    "id": 3,
    "first_name": "Lodovico",
    "last_name": "O'Kane",
    "email": "lokane2@topsy.com",
    "gender": "Male",
    "carmodel": "Dakota"
  },
  {
    "id": 4,
    "first_name": "Ian",
    "last_name": "Spradbery",
    "email": "ispradbery3@ca.gov",
    "gender": "Male",
    "carmodel": "Land Cruiser"
  },
  {
    "id": 5,
    "first_name": "Tabbi",
    "last_name": "Van de Vlies",
    "email": "tvandevlies4@reference.com",
    "gender": "Female",
    "carmodel": "Precis"
  },
  {
    "id": 6,
    "first_name": "Dane",
    "last_name": "Scrimgeour",
    "email": "dscrimgeour5@mail.ru",
    "gender": "Male",
    "carmodel": "Acclaim"
  },
  {
    "id": 7,
    "first_name": "Olwen",
    "last_name": "Barthelmes",
    "email": "obarthelmes6@miibeian.gov.cn",
    "gender": "Female",
    "carmodel": "5 Series"
  },
  {
    "id": 8,
    "first_name": "Donnell",
    "last_name": "Ahmad",
    "email": "dahmad7@cafepress.com",
    "gender": "Male",
    "carmodel": "Grand Am"
  },
  {
    "id": 9,
    "first_name": "Beatrisa",
    "last_name": "Ebbers",
    "email": "bebbers8@hostgator.com",
    "gender": "Female",
    "carmodel": "2500"
  },
  {
    "id": 10,
    "first_name": "Silvie",
    "last_name": "Chevers",
    "email": "schevers9@delicious.com",
    "gender": "Female",
    "carmodel": "Legend"
  },
  {
    "id": 11,
    "first_name": "Ulric",
    "last_name": "Janus",
    "email": "ujanusa@oaic.gov.au",
    "gender": "Male",
    "carmodel": "Mariner"
  },
  {
    "id": 12,
    "first_name": "Marilyn",
    "last_name": "Lamy",
    "email": "mlamyb@moonfruit.com",
    "gender": "Female",
    "carmodel": "A6"
  },
  {
    "id": 13,
    "first_name": "Anders",
    "last_name": "Gianullo",
    "email": "agianulloc@creativecommons.org",
    "gender": "Male",
    "carmodel": "Focus"
  },
  {
    "id": 14,
    "first_name": "Angeli",
    "last_name": "Pendleberry",
    "email": "apendleberryd@live.com",
    "gender": "Male",
    "carmodel": "Mighty Max Macro"
  },
  {
    "id": 15,
    "first_name": "Mandel",
    "last_name": "Churm",
    "email": "mchurme@privacy.gov.au",
    "gender": "Male",
    "carmodel": "Grand Am"
  },
  {
    "id": 16,
    "first_name": "Laverna",
    "last_name": "Pickering",
    "email": "lpickeringf@so-net.ne.jp",
    "gender": "Female",
    "carmodel": "Prizm"
  },
  {
    "id": 17,
    "first_name": "Tobey",
    "last_name": "Guerreiro",
    "email": "tguerreirog@google.de",
    "gender": "Female",
    "carmodel": "Miata MX-5"
  },
  {
    "id": 18,
    "first_name": "Marcella",
    "last_name": "Garnall",
    "email": "mgarnallh@cargocollective.com",
    "gender": "Female",
    "carmodel": "Genesis"
  },
  {
    "id": 19,
    "first_name": "Niki",
    "last_name": "Tertre",
    "email": "ntertrei@bing.com",
    "gender": "Female",
    "carmodel": "Outlander"
  },
  {
    "id": 20,
    "first_name": "Christoph",
    "last_name": "Gosforth",
    "email": "cgosforthj@webs.com",
    "gender": "Male",
    "carmodel": "Cavalier"
  },
  {
    "id": 21,
    "first_name": "Karoly",
    "last_name": "Drake",
    "email": "kdrakek@com.com",
    "gender": "Male",
    "carmodel": "Tahoe"
  },
  {
    "id": 22,
    "first_name": "Farand",
    "last_name": "Chazerand",
    "email": "fchazerandl@businesswire.com",
    "gender": "Female",
    "carmodel": "SLR McLaren"
  },
  {
    "id": 23,
    "first_name": "Edna",
    "last_name": "Smolan",
    "email": "esmolanm@ox.ac.uk",
    "gender": "Female",
    "carmodel": "TSX"
  },
  {
    "id": 24,
    "first_name": "Costanza",
    "last_name": "Spellissy",
    "email": "cspellissyn@columbia.edu",
    "gender": "Female",
    "carmodel": "Venture"
  },
  {
    "id": 25,
    "first_name": "Dew",
    "last_name": "Dugood",
    "email": "ddugoodo@creativecommons.org",
    "gender": "Male",
    "carmodel": "Sonoma Club Coupe"
  },
  {
    "id": 26,
    "first_name": "Cynde",
    "last_name": "Vamplus",
    "email": "cvamplusp@rakuten.co.jp",
    "gender": "Female",
    "carmodel": "Seville"
  },
  {
    "id": 27,
    "first_name": "Lexis",
    "last_name": "Mycock",
    "email": "lmycockq@eepurl.com",
    "gender": "Female",
    "carmodel": "C-Class"
  },
  {
    "id": 28,
    "first_name": "Cello",
    "last_name": "Mainz",
    "email": "cmainzr@java.com",
    "gender": "Male",
    "carmodel": "Galant"
  },
  {
    "id": 29,
    "first_name": "Quinn",
    "last_name": "Dyneley",
    "email": "qdyneleys@stanford.edu",
    "gender": "Female",
    "carmodel": "Neon"
  },
  {
    "id": 30,
    "first_name": "Leroy",
    "last_name": "Martinson",
    "email": "lmartinsont@com.com",
    "gender": "Male",
    "carmodel": "Stratus"
  },
  {
    "id": 31,
    "first_name": "Dorella",
    "last_name": "Glancy",
    "email": "dglancyu@flickr.com",
    "gender": "Female",
    "carmodel": "Range Rover Sport"
  },
  {
    "id": 32,
    "first_name": "Sherry",
    "last_name": "Bau",
    "email": "sbauv@hao123.com",
    "gender": "Female",
    "carmodel": "525"
  },
  {
    "id": 33,
    "first_name": "Gerianna",
    "last_name": "Mc Meekan",
    "email": "gmcmeekanw@prweb.com",
    "gender": "Female",
    "carmodel": "Altima"
  },
  {
    "id": 34,
    "first_name": "Nissie",
    "last_name": "Edmeads",
    "email": "nedmeadsx@usa.gov",
    "gender": "Female",
    "carmodel": "Blazer"
  },
  {
    "id": 35,
    "first_name": "Tova",
    "last_name": "Axworthy",
    "email": "taxworthyy@google.pl",
    "gender": "Female",
    "carmodel": "Grand Am"
  },
  {
    "id": 36,
    "first_name": "Nevsa",
    "last_name": "Gourdon",
    "email": "ngourdonz@51.la",
    "gender": "Female",
    "carmodel": "TSX"
  },
  {
    "id": 37,
    "first_name": "Ave",
    "last_name": "MacColgan",
    "email": "amaccolgan10@gmpg.org",
    "gender": "Male",
    "carmodel": "Firebird"
  },
  {
    "id": 38,
    "first_name": "Meaghan",
    "last_name": "Sancroft",
    "email": "msancroft11@ftc.gov",
    "gender": "Female",
    "carmodel": "New Beetle"
  },
  {
    "id": 39,
    "first_name": "Valry",
    "last_name": "Santino",
    "email": "vsantino12@github.com",
    "gender": "Female",
    "carmodel": "Range Rover"
  },
  {
    "id": 40,
    "first_name": "Lorrie",
    "last_name": "Fowgies",
    "email": "lfowgies13@upenn.edu",
    "gender": "Male",
    "carmodel": "Grand Prix"
  },
  {
    "id": 41,
    "first_name": "Gabrielle",
    "last_name": "Godridge",
    "email": "ggodridge14@nymag.com",
    "gender": "Female",
    "carmodel": "Town Car"
  },
  {
    "id": 42,
    "first_name": "Ring",
    "last_name": "Ablitt",
    "email": "rablitt15@berkeley.edu",
    "gender": "Male",
    "carmodel": "Vibe"
  },
  {
    "id": 43,
    "first_name": "Rikki",
    "last_name": "Kerfod",
    "email": "rkerfod16@ycombinator.com",
    "gender": "Female",
    "carmodel": "Skylark"
  },
  {
    "id": 44,
    "first_name": "Nolan",
    "last_name": "Freddi",
    "email": "nfreddi17@cbsnews.com",
    "gender": "Male",
    "carmodel": "Ram Van B150"
  },
  {
    "id": 45,
    "first_name": "Pernell",
    "last_name": "Folliss",
    "email": "pfolliss18@nationalgeographic.com",
    "gender": "Male",
    "carmodel": "tC"
  }
]
